apicurio_datahub_kafka-2.1.1.dist-info/licenses/LICENSE
apicurio_kafka/__init__.py
apicurio_kafka/apicurio_schema_registry.py
apicurio_datahub_kafka-2.1.1.dist-info/METADATA
apicurio_datahub_kafka-2.1.1.dist-info/WHEEL
apicurio_datahub_kafka-2.1.1.dist-info/top_level.txt
apicurio_datahub_kafka-2.1.1.dist-info/RECORD
