Metadata-Version: 2.4
Name: apicurio_datahub_kafka
Version: 2.1.1
Summary: DataHub ApiCurio Schema Registry for Kafka Source
License-File: LICENSE
Requires-Dist: acryl-datahub[kafka]
Dynamic: description
Dynamic: description-content-type
Dynamic: license-file
Dynamic: requires-dist
Dynamic: summary
